LICENSE
README.md
setup.cfg
setup.py
./kiroframe_importer/__init__.py
./kiroframe_importer/arcee_cl.py
./kiroframe_importer/importer.py
./kiroframe_importer/modules/__init__.py
./kiroframe_importer/modules/mlf.py
kiroframe_importer.egg-info/PKG-INFO
kiroframe_importer.egg-info/SOURCES.txt
kiroframe_importer.egg-info/dependency_links.txt
kiroframe_importer.egg-info/entry_points.txt
kiroframe_importer.egg-info/requires.txt
kiroframe_importer.egg-info/top_level.txt