Metadata-Version: 2.4
Name: kiroframe_importer
Version: 0.0.10
Summary: ML profiling importing tool for Kiroframe
Home-page: https://my.kiroframe.com/
Author: Hystax
License: "Apache License 2.0"
Project-URL: Homepage, https://my.kiroframe.com/
Project-URL: Source, https://github.com/hystax/kiroframe_importer
Keywords: arcee,ml,kiroframe,mlops
Requires-Python: <4,>=3.10
License-File: LICENSE
Requires-Dist: tqdm==4.67.1
Requires-Dist: mlflow==3.3.0
Requires-Dist: retrying==1.4.2
Dynamic: license-file
